crpc/__init__.py
crpc-0.1.1.dist-info/METADATA
crpc-0.1.1.dist-info/WHEEL
crpc-0.1.1.dist-info/top_level.txt
crpc-0.1.1.dist-info/RECORD
