Metadata-Version: 2.4
Name: crpc
Version: 0.1.1
Summary: Cross domain RPC
Author-email: nzturn <nzturn@gmail.com>
Keywords: mqtt,rpc
Classifier: Development Status :: 3 - Alpha
Classifier: Intended Audience :: Developers
Classifier: Programming Language :: Python :: 3
Requires-Python: >=3.8
Requires-Dist: paho_mqtt==1.6.1
